Workbook

Sheet 使用说明
B1: 投资实盘记录 · 假设-概率-归因日志
B2: 核心目的：不是记流水赚了多少，而是证明你的判断“可校准”——说 70% 会兑现，事后真有约 70% 兑现。这对量化/投研岗与未来 LP 都是最硬的可信度。
B4: 填哪些格子
B5: ① 蓝色区（A–O）：建仓当天填，填完就在雪球/公开处发出去、之后不再改。事前锁定不可改，正是真记录和事后编故事的分水岭。
B6: ② 橙色区（P–R、Z）：平仓当天填。实际收益、假设是否兑现（是/部分/否）、复盘一句话。
B7: ③ 灰色区（S–Y）：公式自动算，不要动。
B8: 概率、仓位、收益直接输百分数（如 65%）；概率/仓位限 0–100%，收益可为负。
B10: 关键字段怎么想
B11: • 假设：必须一句话、可证伪。含糊的假设事后无法判定成没成，归因就失效。
B12: • 主观概率：你认为“假设成立”的概率，是校准分析的输入，逼自己给依据而非拍脑袋。
B13: • 失效条件(kill)：出现什么就认错离场。事前写死，防止事后合理化。
B14: • invest-infer 边/机制：这笔靠哪条传导逻辑（supplies/demands…）。用于分机制统计哪种逻辑真有效、哪种是幻觉。
... B29: 说明：本表为空白模板，公式已内置。“交易日志”第 4 行为示例行，理解格式后可整行删除。本文件不构成投资建议。

Sheet 列表
A1: invest-infer 边/机制 | B1: 策略标签 | C1: 假设是否兑现
A2: supplies | B2: 大账户·质量成长 | C2: 是
A3: supplies_to | B3: 小账户·题材事件 | C3: 部分
A4: demands | B4: β母层 | C4: 否
A5: implements | B5: 逆向/困境反转
A6: masters | B6: 其他
A7: certified_by
A8: located_in
A9: affects
A10: substitutes
A11: competes_with
A12: complements
A13: belongs_to
A14: 宏观/政策
A15: 情绪/资金
A16: 其他

Sheet 交易日志
A1: 投资实盘记录 · 假设-概率-归因日志
A2: ① 建仓时锁定（发布后不修改） | P2: ② 平仓时填写 | S2: ③ 自动计算（勿改） | Z2: ④ 平仓复盘
A3: 编号 | B3: 建仓日期 | C3: 标的 | D3: 代码 | E3: 假设（可证伪·一句话） | F3: 关键驱动 / 逻辑链 | G3: invest-infer 边/机制 | H3: 主观概率 | I3: 概率依据 | J3: 兑现路径与时间窗 | K3: 失效条件（kill） | L3: 仓位% | M3: 预期盈亏比 | N3: 目标价/止损 | O3: 策略标签 | P3: 平仓日期 | Q3: 实际收益% | R3: 假设是否兑现 | S3: 兑现数值 | T3: 归因象限 | U3: 持仓天数 | V3: 账户贡献 | W3: 预测平方误差 | X3: 累计账户收益 | Y3: 回撤 | Z3: 复盘（一句话）
A4: 1 | B4: Wed Jul 15 2026 08:00:00 GMT+0800 (China Standard Time) | C4: 永新光学 | D4: 603297 | E4: 车载镜头放量驱动 25H2 营收加速，市占率提升逻辑兑现 | F4: 下游车载需求→镜头订单→营收（demands 逆链上传 + supplies） | G4: demands | H4: 0.65 | I4: Q2 调研车载订单环比+30%，大客户导入进度超预期 | J4: 25Q3 营收同比>25% 且车载占比提升（窗口 3 个月） | K4: 车载营收环比转负 或 大客户砍单 | L4: 0.08 | M4: 2.5 | N4: 目标92/止损76 | O4: 大账户·质量成长 | P4: Sun Sep 20 2026 08:00:00 GMT+0800 (China Standard Time) | Q4: 0.14 | R4: 是 | S4: =IF(R4="","",IF(R4="是",1,IF(R4="部分",0.5,0))) -> 1 | T4: =IF(OR(Q4="",R4=""),"",IF(OR(R4="是",R4="部分"),IF(Q4>0,"对且赚","对但亏"),IF(Q4>0,"错但赚","错且亏"))) -> 对且赚 | U4: =IF(OR(P4="",B4=""),"",P4-B4) -> #VALUE! | V4: =IF(OR(L4="",Q4=""),"",L4*Q4) -> 0.0112 | W4: =IF(OR(H4="",S4=""),"",(H4-S4)^2) -> 0.1225 | X4: =IF(Q4="","",SUM($V$4:V4)) -> 0.0112 | Y4: =IF(X4="","",X4-MAX($X$4:X4)) -> 0 | Z4: 逻辑如期兑现且盈利；车载放量确认，回看仓位可更重 | AB4: ← 示例行，理解格式后可整行删除
A5: 2 | B5: 46286 | C5: 柏诚股份 | D5: 60113 | E5: 半导体资本开支进入新一轮扩张周期，柏诚超大规模半导体洁净室订单将在未来6–18个月持续转化为收入和利润，使公司利润增速显著高于市场当前定价。 | F5: 半导体扩产 → 洁净室属于资本开支前置环节 → 洁净室订单先增长 → 柏诚新签/在手订单爆发 → 2026H2–2027进入密集执行 → 收入确认加速 → 毛利率改善 → 利润弹性释放 → 市场重新定价 | H5: 0.7 | I5: 2026H1新签订单 58.33亿元，已经超过2025全年；其中半导体及泛半导体 45.84亿元，占78.6%。6月底在手订单 56.29亿元，同比+222.15%；7/1–8/25又新增订单 10.34亿元，其中境内半导体占83.73%。订单已经从“预期”进入“已签合同”阶段。 | J5: **2026Q4：**订单执行加速；**2027H1：**大规模订单进入收入确认；**2027H2：**利润弹性进一步释放；若半导体CAPEX继续扩张，2028年仍可能维持较高订单景气。公司披露项目正常密集执行期约 6–12个月。 | K5: ① 在手订单无法按计划转收入；② 半导体客户扩产明显放缓/取消；③ 新订单增速明显下降；④ 毛利率重新持续下滑；⑤ 2027年收入增长无法兑现当前订单基础；⑥ 大规模订单带来收入增长但利润率不升反降，说明“订单→利润”的传导机制失效 | L5: 0.93 | M5: 0.12569444 | N5: 40/22 | O5: 小账户·题材事件 | S5: =IF(R5="","",IF(R5="是",1,IF(R5="部分",0.5,0))) | T5: =IF(OR(Q5="",R5=""),"",IF(OR(R5="是",R5="部分"),IF(Q5>0,"对且赚","对但亏"),IF(Q5>0,"错但赚","错且亏"))) | U5: =IF(OR(P5="",B5=""),"",P5-B5) | V5: =IF(OR(L5="",Q5=""),"",L5*Q5) | W5: =IF(OR(H5="",S5=""),"",(H5-S5)^2) | X5: =IF(Q5="","",SUM($V$4:V5)) | Y5: =IF(X5="","",X5-MAX($X$4:X5))
A6: 3 | S6: =IF(R6="","",IF(R6="是",1,IF(R6="部分",0.5,0))) | T6: =IF(OR(Q6="",R6=""),"",IF(OR(R6="是",R6="部分"),IF(Q6>0,"对且赚","对但亏"),IF(Q6>0,"错但赚","错且亏"))) | U6: =IF(OR(P6="",B6=""),"",P6-B6) | V6: =IF(OR(L6="",Q6=""),"",L6*Q6) | W6: =IF(OR(H6="",S6=""),"",(H6-S6)^2) | X6: =IF(Q6="","",SUM($V$4:V6)) | Y6: =IF(X6="","",X6-MAX($X$4:X6))
A7: 4 | S7: =IF(R7="","",IF(R7="是",1,IF(R7="部分",0.5,0))) | T7: =IF(OR(Q7="",R7=""),"",IF(OR(R7="是",R7="部分"),IF(Q7>0,"对且赚","对但亏"),IF(Q7>0,"错但赚","错且亏"))) | U7: =IF(OR(P7="",B7=""),"",P7-B7) | V7: =IF(OR(L7="",Q7=""),"",L7*Q7) | W7: =IF(OR(H7="",S7=""),"",(H7-S7)^2) | X7: =IF(Q7="","",SUM($V$4:V7)) | Y7: =IF(X7="","",X7-MAX($X$4:X7))
A8: 5 | S8: =IF(R8="","",IF(R8="是",1,IF(R8="部分",0.5,0))) | T8: =IF(OR(Q8="",R8=""),"",IF(OR(R8="是",R8="部分"),IF(Q8>0,"对且赚","对但亏"),IF(Q8>0,"错但赚","错且亏"))) | U8: =IF(OR(P8="",B8=""),"",P8-B8) | V8: =IF(OR(L8="",Q8=""),"",L8*Q8) | W8: =IF(OR(H8="",S8=""),"",(H8-S8)^2) | X8: =IF(Q8="","",SUM($V$4:V8)) | Y8: =IF(X8="","",X8-MAX($X$4:X8))
A9: 6 | S9: =IF(R9="","",IF(R9="是",1,IF(R9="部分",0.5,0))) | T9: =IF(OR(Q9="",R9=""),"",IF(OR(R9="是",R9="部分"),IF(Q9>0,"对且赚","对但亏"),IF(Q9>0,"错但赚","错且亏"))) | U9: =IF(OR(P9="",B9=""),"",P9-B9) | V9: =IF(OR(L9="",Q9=""),"",L9*Q9) | W9: =IF(OR(H9="",S9=""),"",(H9-S9)^2) | X9: =IF(Q9="","",SUM($V$4:V9)) | Y9: =IF(X9="","",X9-MAX($X$4:X9))
A10: 7 | S10: =IF(R10="","",IF(R10="是",1,IF(R10="部分",0.5,0))) | T10: =IF(OR(Q10="",R10=""),"",IF(OR(R10="是",R10="部分"),IF(Q10>0,"对且赚","对但亏"),IF(Q10>0,"错但赚","错且亏"))) | U10: =IF(OR(P10="",B10=""),"",P10-B10) | V10: =IF(OR(L10="",Q10=""),"",L10*Q10) | W10: =IF(OR(H10="",S10=""),"",(H10-S10)^2) | X10: =IF(Q10="","",SUM($V$4:V10)) | Y10: =IF(X10="","",X10-MAX($X$4:X10))
A11: 8 | S11: =IF(R11="","",IF(R11="是",1,IF(R11="部分",0.5,0))) | T11: =IF(OR(Q11="",R11=""),"",IF(OR(R11="是",R11="部分"),IF(Q11>0,"对且赚","对但亏"),IF(Q11>0,"错但赚","错且亏"))) | U11: =IF(OR(P11="",B11=""),"",P11-B11) | V11: =IF(OR(L11="",Q11=""),"",L11*Q11) | W11: =IF(OR(H11="",S11=""),"",(H11-S11)^2) | X11: =IF(Q11="","",SUM($V$4:V11)) | Y11: =IF(X11="","",X11-MAX($X$4:X11))
A12: 9 | S12: =IF(R12="","",IF(R12="是",1,IF(R12="部分",0.5,0))) | T12: =IF(OR(Q12="",R12=""),"",IF(OR(R12="是",R12="部分"),IF(Q12>0,"对且赚","对但亏"),IF(Q12>0,"错但赚","错且亏"))) | U12: =IF(OR(P12="",B12=""),"",P12-B12) | V12: =IF(OR(L12="",Q12=""),"",L12*Q12) | W12: =IF(OR(H12="",S12=""),"",(H12-S12)^2) | X12: =IF(Q12="","",SUM($V$4:V12)) | Y12: =IF(X12="","",X12-MAX($X$4:X12))
A13: 10 | S13: =IF(R13="","",IF(R13="是",1,IF(R13="部分",0.5,0))) | T13: =IF(OR(Q13="",R13=""),"",IF(OR(R13="是",R13="部分"),IF(Q13>0,"对且赚","对但亏"),IF(Q13>0,"错但赚","错且亏"))) | U13: =IF(OR(P13="",B13=""),"",P13-B13) | V13: =IF(OR(L13="",Q13=""),"",L13*Q13) | W13: =IF(OR(H13="",S13=""),"",(H13-S13)^2) | X13: =IF(Q13="","",SUM($V$4:V13)) | Y13: =IF(X13="","",X13-MAX($X$4:X13))
A14: 11 | S14: =IF(R14="","",IF(R14="是",1,IF(R14="部分",0.5,0))) | T14: =IF(OR(Q14="",R14=""),"",IF(OR(R14="是",R14="部分"),IF(Q14>0,"对且赚","对但亏"),IF(Q14>0,"错但赚","错且亏"))) | U14: =IF(OR(P14="",B14=""),"",P14-B14) | V14: =IF(OR(L14="",Q14=""),"",L14*Q14) | W14: =IF(OR(H14="",S14=""),"",(H14-S14)^2) | X14: =IF(Q14="","",SUM($V$4:V14)) | Y14: =IF(X14="","",X14-MAX($X$4:X14))
A15: 12 | S15: =IF(R15="","",IF(R15="是",1,IF(R15="部分",0.5,0))) | T15: =IF(OR(Q15="",R15=""),"",IF(OR(R15="是",R15="部分"),IF(Q15>0,"对且赚","对但亏"),IF(Q15>0,"错但赚","错且亏"))) | U15: =IF(OR(P15="",B15=""),"",P15-B15) | V15: =IF(OR(L15="",Q15=""),"",L15*Q15) | W15: =IF(OR(H15="",S15=""),"",(H15-S15)^2) | X15: =IF(Q15="","",SUM($V$4:V15)) | Y15: =IF(X15="","",X15-MAX($X$4:X15))
A16: 13 | S16: =IF(R16="","",IF(R16="是",1,IF(R16="部分",0.5,0))) | T16: =IF(OR(Q16="",R16=""),"",IF(OR(R16="是",R16="部分"),IF(Q16>0,"对且赚","对但亏"),IF(Q16>0,"错但赚","错且亏"))) | U16: =IF(OR(P16="",B16=""),"",P16-B16) | V16: =IF(OR(L16="",Q16=""),"",L16*Q16) | W16: =IF(OR(H16="",S16=""),"",(H16-S16)^2) | X16: =IF(Q16="","",SUM($V$4:V16)) | Y16: =IF(X16="","",X16-MAX($X$4:X16))
A17: 14 | S17: =IF(R17="","",IF(R17="是",1,IF(R17="部分",0.5,0))) | T17: =IF(OR(Q17="",R17=""),"",IF(OR(R17="是",R17="部分"),IF(Q17>0,"对且赚","对但亏"),IF(Q17>0,"错但赚","错且亏"))) | U17: =IF(OR(P17="",B17=""),"",P17-B17) | V17: =IF(OR(L17="",Q17=""),"",L17*Q17) | W17: =IF(OR(H17="",S17=""),"",(H17-S17)^2) | X17: =IF(Q17="","",SUM($V$4:V17)) | Y17: =IF(X17="","",X17-MAX($X$4:X17))
... A203: 200 | S203: =IF(R203="","",IF(R203="是",1,IF(R203="部分",0.5,0))) | T203: =IF(OR(Q203="",R203=""),"",IF(OR(R203="是",R203="部分"),IF(Q203>0,"对且赚","对但亏"),IF(Q203>0,"错但赚","错且亏"))) | U203: =IF(OR(P203="",B203=""),"",P203-B203) | V203: =IF(OR(L203="",Q203=""),"",L203*Q203) | W203: =IF(OR(H203="",S203=""),"",(H203-S203)^2) | X203: =IF(Q203="","",SUM($V$4:V203)) | Y203: =IF(X203="","",X203-MAX($X$4:X203))

Sheet 看板
A1: 校准与归因看板
A3: 一、概览 | D3: 五、校准表
A4: 总记录数 | B4: =COUNTA(交易日志!$C$4:$C$203) -> 2 | D4: 概率区间 | E4: 预测中值 | F4: 样本数 | G4: 实际兑现率
A5: 已平仓 | B5: =COUNT(交易日志!$Q$4:$Q$203) -> 1 | D5: <50% | E5: 0.45 | F5: =COUNTIFS(交易日志!$H$4:$H$203,">="&$I5,交易日志!$H$4:$H$203,"<"&$J5,交易日志!$R$4:$R$203,"<>") -> 0 | G5: =IFERROR(AVERAGEIFS(交易日志!$S$4:$S$203,交易日志!$H$4:$H$203,">="&$I5,交易日志!$H$4:$H$203,"<"&$J5,交易日志!$R$4:$R$203,"<>"),"—") -> — | I5: 0 | J5: 0.5 | K5: =IF($F5=0,$E5,$G5) -> 0.45
A6: 持仓中 | B6: =B4-B5 -> 1 | D6: 50–60% | E6: 0.55 | F6: =COUNTIFS(交易日志!$H$4:$H$203,">="&$I6,交易日志!$H$4:$H$203,"<"&$J6,交易日志!$R$4:$R$203,"<>") -> 0 | G6: =IFERROR(AVERAGEIFS(交易日志!$S$4:$S$203,交易日志!$H$4:$H$203,">="&$I6,交易日志!$H$4:$H$203,"<"&$J6,交易日志!$R$4:$R$203,"<>"),"—") -> — | I6: 0.5 | J6: 0.6 | K6: =IF($F6=0,$E6,$G6) -> 0.55
D7: 60–70% | E7: 0.65 | F7: =COUNTIFS(交易日志!$H$4:$H$203,">="&$I7,交易日志!$H$4:$H$203,"<"&$J7,交易日志!$R$4:$R$203,"<>") -> 1 | G7: =IFERROR(AVERAGEIFS(交易日志!$S$4:$S$203,交易日志!$H$4:$H$203,">="&$I7,交易日志!$H$4:$H$203,"<"&$J7,交易日志!$R$4:$R$203,"<>"),"—") -> 1 | I7: 0.6 | J7: 0.7 | K7: =IF($F7=0,$E7,$G7) -> 1
A8: 二、双胜率 | D8: 70–80% | E8: 0.75 | F8: =COUNTIFS(交易日志!$H$4:$H$203,">="&$I8,交易日志!$H$4:$H$203,"<"&$J8,交易日志!$R$4:$R$203,"<>") -> 0 | G8: =IFERROR(AVERAGEIFS(交易日志!$S$4:$S$203,交易日志!$H$4:$H$203,">="&$I8,交易日志!$H$4:$H$203,"<"&$J8,交易日志!$R$4:$R$203,"<>"),"—") -> — | I8: 0.7 | J8: 0.8 | K8: =IF($F8=0,$E8,$G8) -> 0.75
A9: 假设兑现率（部分计0.5） | B9: =IFERROR(AVERAGE(交易日志!$S$4:$S$203),"—") -> 1 | D9: 80–90% | E9: 0.85 | F9: =COUNTIFS(交易日志!$H$4:$H$203,">="&$I9,交易日志!$H$4:$H$203,"<"&$J9,交易日志!$R$4:$R$203,"<>") -> 0 | G9: =IFERROR(AVERAGEIFS(交易日志!$S$4:$S$203,交易日志!$H$4:$H$203,">="&$I9,交易日志!$H$4:$H$203,"<"&$J9,交易日志!$R$4:$R$203,"<>"),"—") -> — | I9: 0.8 | J9: 0.9 | K9: =IF($F9=0,$E9,$G9) -> 0.85
A10: 盈亏胜率 | B10: =IFERROR(COUNTIF(交易日志!$Q$4:$Q$203,">0")/COUNT(交易日志!$Q$4:$Q$203),"—") -> 1 | D10: ≥90% | E10: 0.95 | F10: =COUNTIFS(交易日志!$H$4:$H$203,">="&$I10,交易日志!$H$4:$H$203,"<"&$J10,交易日志!$R$4:$R$203,"<>") -> 0 | G10: =IFERROR(AVERAGEIFS(交易日志!$S$4:$S$203,交易日志!$H$4:$H$203,">="&$I10,交易日志!$H$4:$H$203,"<"&$J10,交易日志!$R$4:$R$203,"<>"),"—") -> — | I10: 0.9 | J10: 1.01 | K10: =IF($F10=0,$E10,$G10) -> 0.95
A11: 差值（兑现-盈亏） | B11: =IFERROR(B9-B10,"—") -> 0
D12: 右图：点越贴近对角线，说明你的概率越校准。样本数=0 的区间，点默认落在对角线上（即无信息）。
A13: 三、归因四象限（占已平仓）
A14: 对且赚（真alpha） | B14: =IFERROR(COUNTIF(交易日志!$T$4:$T$203,"对且赚")/$B$5,"—") -> 1
A15: 对但亏（择时/执行） | B15: =IFERROR(COUNTIF(交易日志!$T$4:$T$203,"对但亏")/$B$5,"—") -> 0
A16: 错但赚（运气·警惕） | B16: =IFERROR(COUNTIF(交易日志!$T$4:$T$203,"错但赚")/$B$5,"—") -> 0
A17: 错且亏（被正确惩罚） | B17: =IFERROR(COUNTIF(交易日志!$T$4:$T$203,"错且亏")/$B$5,"—") -> 0
A19: 四、风险与效率
A20: 盈亏比（均盈/均亏） | B20: =IFERROR(AVERAGEIF(交易日志!$Q$4:$Q$203,">0")/ABS(AVERAGEIF(交易日志!$Q$4:$Q$203,"<0")),"—") -> —
A21: 平均持仓天数 | B21: =IFERROR(AVERAGE(交易日志!$U$4:$U$203),"—") -> —
A22: Brier 分数（越低越好） | B22: =IFERROR(AVERAGE(交易日志!$W$4:$W$203),"—") -> 0.1225
A23: 最大回撤（按录入顺序） | B23: =IFERROR(MIN(交易日志!$Y$4:$Y$203),"—") -> 0
